libmav.cpython-310-darwin.so
libmav-0.0.6.dist-info/RECORD
libmav-0.0.6.dist-info/LICENSE
libmav-0.0.6.dist-info/WHEEL
libmav-0.0.6.dist-info/top_level.txt
libmav-0.0.6.dist-info/METADATA
