Metadata-Version: 2.1
Name: libmav
Version: 0.0.6
Summary: A library for the MAVLink protocol
Author: Auterion
Author-email: success@auterion.com
Requires-Python: >=3.7
License-File: LICENSE
Provides-Extra: test
Requires-Dist: pytest>=6.0; extra == "test"
